{
  "version": "16.0.0",
  "files": {
    "9b6f9e0c28cca71794382393db3f40e215bfd934fbb1b0249a8155ee02d9c954": {
      "source": {
        "path": "RDS.template.json",
        "packaging": "file"
      },
      "destinations": {
        "current_account-current_region": {
          "bucketName": "cdk-hnb659fds-assets-${AWS::AccountId}-${AWS::Region}",
          "objectKey": "9b6f9e0c28cca71794382393db3f40e215bfd934fbb1b0249a8155ee02d9c954.json",
          "assumeRoleArn": "arn:${AWS::Partition}:iam::${AWS::AccountId}:role/cdk-hnb659fds-file-publishing-role-${AWS::AccountId}-${AWS::Region}"
        }
      }
    }
  },
  "dockerImages": {}
}